{
  "@context": "https://wcrp-cmip.github.io/MIP_variables/data_descriptors/variables/_context",
  "id": "aeday.zg100.json",
  "type": "mip-variable",
  "mip-tables": [
    {
      "id": "aeday.json",
      "mip-era": "cmip6"
    },
    {
      "id": "aeday.json",
      "mip-era": "cmip6plus"
    }
  ],
  "themes": [
    "TBC"
  ],
  "cell_measures": "area: areacella",
  "cell_methods": "area: time: mean",
  "comment": "Geopotential height on the 100 hPa surface",
  "dimensions": [
    "longitude",
    "latitude",
    "time",
    "p100"
  ],
  "frequency": "day",
  "long_name": "Geopotential Height at 100hPa",
  "modeling_realm": [
    "aerosol"
  ],
  "ok_max_mean_abs": "",
  "ok_min_mean_abs": "",
  "out_name": "zg100",
  "positive": "",
  "standard_name": "geopotential_height",
  "units": "m",
  "valid_max": "",
  "valid_min": "",
  "dtype": "real"
}