{
  "@context": "https://wcrp-cmip.github.io/MIP_variables/data_descriptors/variables/_context",
  "id": "apmonlev.tnhusscpbl.json",
  "type": "mip-variable",
  "mip_tables": [
    {
      "id": "apmonlev.json",
      "mip-era": "cmip6"
    },
    {
      "id": "apmonlev.json",
      "mip-era": "cmip6plus"
    }
  ],
  "themes": [
    "TBC"
  ],
  "cell_measures": "area: areacella",
  "cell_methods": "area: time: mean",
  "comment": "Tendency of Specific Humidity Due to Stratiform Cloud and Precipitation and Boundary Layer Mixing  (to be specified only in  models which do not separate budget terms for stratiform cloud, precipitation and boundary layer schemes.  Includes all boundary layer terms including and diffusive terms.)",
  "dimensions": [
    "longitude",
    "latitude",
    "alevel",
    "time"
  ],
  "frequency": "mon",
  "long_name": "Tendency of Specific Humidity Due to Stratiform Cloud and Precipitation and Boundary Layer Mixing",
  "modeling_realm": [
    "atmos"
  ],
  "ok_max_mean_abs": "",
  "ok_min_mean_abs": "",
  "out_name": "tnhusscpbl",
  "positive": "",
  "standard_name": "tendency_of_specific_humidity_due_to_stratiform_cloud_and_precipitation_and_boundary_layer_mixing",
  "units": "s-1",
  "valid_max": "",
  "valid_min": "",
  "dtype": "real"
}