{
  "@context": "https://wcrp-cmip.github.io/MIP_variables/data_descriptors/variables/_context",
  "id": "lpmon.burntfractionall.json",
  "type": "mip-variable",
  "mip_tables": [
    {
      "id": "lpmon.json",
      "mip-era": "cmip6"
    },
    {
      "id": "lpmon.json",
      "mip-era": "cmip6plus"
    }
  ],
  "themes": [
    "TBC"
  ],
  "cell_measures": "area: areacella",
  "cell_methods": "area: mean where land over all_area_types time: mean",
  "comment": "Percentage of grid cell burned due to all fires including natural and anthropogenic fires and those associated with anthropogenic Land-use change",
  "dimensions": [
    "longitude",
    "latitude",
    "time",
    "typeburnt"
  ],
  "frequency": "mon",
  "long_name": "Percentage of Entire Grid Cell That Is Covered by Burnt Vegetation (All Classes)",
  "modeling_realm": [
    "land"
  ],
  "ok_max_mean_abs": "",
  "ok_min_mean_abs": "",
  "out_name": "burntFractionAll",
  "positive": "",
  "standard_name": "area_fraction",
  "units": "%",
  "valid_max": "",
  "valid_min": "",
  "dtype": "real"
}