{
  "@context": "https://wcrp-cmip.github.io/MIP_variables/data_descriptors/variables/_context",
  "id": "lpmon.fnup.json",
  "type": "mip-variable",
  "mip_tables": [
    {
      "id": "lpmon.json",
      "mip-era": "cmip6"
    },
    {
      "id": "lpmon.json",
      "mip-era": "cmip6plus"
    }
  ],
  "themes": [
    "TBC"
  ],
  "cell_measures": "area: areacella",
  "cell_methods": "area: mean where land time: mean",
  "comment": "The uptake of nitrogen by fixation: nitrogen fixation means the uptake of nitrogen gas directly from the atmosphere. ",
  "dimensions": [
    "longitude",
    "latitude",
    "time"
  ],
  "frequency": "mon",
  "long_name": "Total Plant Nitrogen Uptake (Sum of Ammonium and Nitrate) Irrespective of the Source of Nitrogen",
  "modeling_realm": [
    "land"
  ],
  "ok_max_mean_abs": "",
  "ok_min_mean_abs": "",
  "out_name": "fNup",
  "positive": "",
  "standard_name": "tendency_of_vegetation_mass_content_of_nitrogen_compounds_expressed_as_nitrogen_due_to_fixation",
  "units": "kg m-2 s-1",
  "valid_max": "",
  "valid_min": "",
  "dtype": "real"
}