{
  "@context": "https://wcrp-cmip.github.io/MIP_variables/data_descriptors/variables/_context",
  "id": "lpmon.fahlut.json",
  "type": "mip-variable",
  "mip-tables": [
    {
      "id": "lpmon.json",
      "mip-era": "cmip6"
    },
    {
      "id": "lpmon.json",
      "mip-era": "cmip6plus"
    }
  ],
  "themes": [
    "TBC"
  ],
  "cell_measures": "area: areacella",
  "cell_methods": "area: time: mean where sector",
  "comment": "Anthropogenic heat flux generated from non-renewable human primary energy consumption, including energy use by vehicles, commercial and residential buildings, industry, and power plants.  Primary energy refers to energy in natural resources, fossil and nonfossil, before conversion into other forms, such as electricity.",
  "dimensions": [
    "longitude",
    "latitude",
    "landUse",
    "time"
  ],
  "frequency": "mon",
  "long_name": "Anthropogenic Heat Flux Generated from non-Renewable Human Primary Energy Consumption",
  "modeling_realm": [
    "land"
  ],
  "ok_max_mean_abs": "",
  "ok_min_mean_abs": "",
  "out_name": "fahLut",
  "positive": "up",
  "standard_name": "surface_upward_heat_flux_due_to_anthropogenic_energy_consumption",
  "units": "W m-2",
  "valid_max": "",
  "valid_min": "",
  "dtype": "real"
}