{
  "@context": "https://wcrp-cmip.github.io/CMIP6Plus_MIP_variables/data_descriptors/variables/_context",
  "id": "obmonlev.chlcalc.json",
  "type": "mip-variable",
  "mip-tables": [
    {
      "id": "obmonlev.json",
      "mip-era": "cmip6"
    },
    {
      "id": "obmonlev.json",
      "mip-era": "cmip6plus"
    }
  ],
  "themes": [
    "TBC"
  ],
  "cell_measures": "area: areacello volume: volcello",
  "cell_methods": "area: mean where sea time: mean",
  "comment": "chlorophyll concentration from the calcite-producing phytoplankton component alone",
  "dimensions": [
    "longitude",
    "latitude",
    "olevel",
    "time"
  ],
  "frequency": "mon",
  "long_name": "Mass Concentration of Calcareous Phytoplankton Expressed as Chlorophyll in Sea Water",
  "modeling_realm": [
    "ocnBgchem"
  ],
  "ok_max_mean_abs": "",
  "ok_min_mean_abs": "",
  "out_name": "chlcalc",
  "positive": "",
  "standard_name": "mass_concentration_of_calcareous_phytoplankton_expressed_as_chlorophyll_in_sea_water",
  "units": "kg m-3",
  "valid_max": "",
  "valid_min": "",
  "dtype": "real"
}